dbt_power_tools-0.1.1.dist-info/licenses/LICENSE
dbt_tools/__init__.py
dbt_tools/cli.py
dbt_tools/util.py
dbt_tools/backends/base.py
dbt_tools/backends/ollama_backend.py
dbt_tools/backends/openai_backend.py
dbt_tools/database_connectors/database_connector.py
dbt_tools/dbt_io/loader.py
dbt_tools/dbt_io/selector.py
dbt_tools/dbt_io/writer.py
dbt_power_tools-0.1.1.dist-info/METADATA
dbt_power_tools-0.1.1.dist-info/WHEEL
dbt_power_tools-0.1.1.dist-info/entry_points.txt
dbt_power_tools-0.1.1.dist-info/top_level.txt
dbt_power_tools-0.1.1.dist-info/RECORD
