Metadata-Version: 2.4
Name: dbt-power-tools
Version: 0.1.1
Summary: CLI to auto-generate dbt docs using LLMs (Ollama-first).
Author: Rahul Rajasekharan
Requires-Python: >=3.9
License-File: LICENSE
Requires-Dist: typer>=0.12
Requires-Dist: rich>=13.7
Requires-Dist: pydantic>=2.7
Requires-Dist: ruamel.yaml>=0.18
Requires-Dist: jinja2>=3.1
Requires-Dist: ollama>=0.3.0
Requires-Dist: openai>=2.7.2
Requires-Dist: pandas>=2.3.3
Requires-Dist: SQLAlchemy>=2.0.44
Dynamic: license-file
